.DS_Store
NEMbox/.DS_Store
NEMbox/__init__.py
NEMbox/__main__.py
NEMbox/__version__.py
NEMbox/api.py
NEMbox/cache.py
NEMbox/cmd_parser.py
NEMbox/config.py
NEMbox/const.py
NEMbox/encrypt.py
NEMbox/kill_thread.py
NEMbox/logger.py
NEMbox/menu.py
NEMbox/osdlyrics.py
NEMbox/player.py
NEMbox/scrollstring.py
NEMbox/singleton.py
NEMbox/storage.py
NEMbox/terminalsize.py
NEMbox/ui.py
NEMbox/utils.py
NEMbox/__pycache__/__init__.cpython-37.pyc
NEMbox/__pycache__/__main__.cpython-37.pyc
NEMbox/__pycache__/__version__.cpython-37.pyc
NEMbox/__pycache__/api.cpython-37.pyc
NEMbox/__pycache__/cache.cpython-37.pyc
NEMbox/__pycache__/config.cpython-37.pyc
NEMbox/__pycache__/const.cpython-37.pyc
NEMbox/__pycache__/encrypt.cpython-37.pyc
NEMbox/__pycache__/kill_thread.cpython-37.pyc
NEMbox/__pycache__/logger.cpython-37.pyc
NEMbox/__pycache__/menu.cpython-37.pyc
NEMbox/__pycache__/osdlyrics.cpython-37.pyc
NEMbox/__pycache__/player.cpython-37.pyc
NEMbox/__pycache__/scrollstring.cpython-37.pyc
NEMbox/__pycache__/singleton.cpython-37.pyc
NEMbox/__pycache__/storage.cpython-37.pyc
NEMbox/__pycache__/terminalsize.cpython-37.pyc
NEMbox/__pycache__/ui.cpython-37.pyc
NEMbox/__pycache__/utils.cpython-37.pyc
NEMbox/tests/__init__.py
NEMbox/tests/test_api.py
NEMbox/tests/__pycache__/__init__.cpython-37.pyc
NEMbox/tests/__pycache__/test_api.cpython-37.pyc
macmusicbox-0.2.5.5.2.dist-info/LICENSE.txt
macmusicbox-0.2.5.5.2.dist-info/METADATA
macmusicbox-0.2.5.5.2.dist-info/WHEEL
macmusicbox-0.2.5.5.2.dist-info/entry_points.txt
macmusicbox-0.2.5.5.2.dist-info/top_level.txt
macmusicbox-0.2.5.5.2.dist-info/RECORD
