Metadata-Version: 2.1
Name: macmusicbox
Version: 0.2.5.5.2
Summary: A sexy command line interface musicbox for mac and linux
Home-page: https://github.com/wangjianyuan10/musicbox
Author: walker
Author-email: wangjianyuan10@163.com
License: MIT
Keywords: music,netease,cli,player
Platform: UNKNOWN
Classifier: Development Status :: 4 - Beta
Classifier: Intended Audience :: Developers
Classifier: License :: OSI Approved :: MIT License
Classifier: Natural Language :: English
Classifier: Operating System :: OS Independent
Classifier: Programming Language :: Python
Classifier: Programming Language :: Python :: 3.5
Classifier: Programming Language :: Python :: 3.6
Classifier: Programming Language :: Python :: 3.7
Classifier: Programming Language :: Python :: Implementation :: CPython
Classifier: Topic :: Multimedia :: Sound/Audio
Requires-Dist: requests-cache
Requires-Dist: pycryptodomex
Requires-Dist: future
